libcrypto/__init__.py
libcrypto/_version.py
libcrypto/addresses.py
libcrypto/bip32.py
libcrypto/cli.py
libcrypto/constants.py
libcrypto/formats.py
libcrypto/hash.py
libcrypto/keys.py
libcrypto/mnemonic.py
libcrypto/secp256k1.py
libcrypto/wallet.py
libcrypto/cryptod/__init__.py
libcrypto/cryptod/bench_monty.py
libcrypto/cryptod/compiler_opt.py
libcrypto/cryptod/pct-speedtest.py
libcrypto/cryptod/setup.py
libcrypto/cryptod/Crypto/__init__.py
libcrypto/cryptod/Crypto/__init__.pyi
libcrypto/cryptod/Crypto/py.typed
libcrypto/cryptod/Crypto/Cipher/AES.py
libcrypto/cryptod/Crypto/Cipher/AES.pyi
libcrypto/cryptod/Crypto/Cipher/ARC2.py
libcrypto/cryptod/Crypto/Cipher/ARC2.pyi
libcrypto/cryptod/Crypto/Cipher/ARC4.py
libcrypto/cryptod/Crypto/Cipher/ARC4.pyi
libcrypto/cryptod/Crypto/Cipher/Blowfish.py
libcrypto/cryptod/Crypto/Cipher/Blowfish.pyi
libcrypto/cryptod/Crypto/Cipher/CAST.py
libcrypto/cryptod/Crypto/Cipher/CAST.pyi
libcrypto/cryptod/Crypto/Cipher/ChaCha20.py
libcrypto/cryptod/Crypto/Cipher/ChaCha20.pyi
libcrypto/cryptod/Crypto/Cipher/ChaCha20_Poly1305.py
libcrypto/cryptod/Crypto/Cipher/ChaCha20_Poly1305.pyi
libcrypto/cryptod/Crypto/Cipher/DES.py
libcrypto/cryptod/Crypto/Cipher/DES.pyi
libcrypto/cryptod/Crypto/Cipher/DES3.py
libcrypto/cryptod/Crypto/Cipher/DES3.pyi
libcrypto/cryptod/Crypto/Cipher/PKCS1_OAEP.py
libcrypto/cryptod/Crypto/Cipher/PKCS1_OAEP.pyi
libcrypto/cryptod/Crypto/Cipher/PKCS1_v1_5.py
libcrypto/cryptod/Crypto/Cipher/PKCS1_v1_5.pyi
libcrypto/cryptod/Crypto/Cipher/Salsa20.py
libcrypto/cryptod/Crypto/Cipher/Salsa20.pyi
libcrypto/cryptod/Crypto/Cipher/_EKSBlowfish.py
libcrypto/cryptod/Crypto/Cipher/_EKSBlowfish.pyi
libcrypto/cryptod/Crypto/Cipher/__init__.py
libcrypto/cryptod/Crypto/Cipher/__init__.pyi
libcrypto/cryptod/Crypto/Cipher/_mode_cbc.py
libcrypto/cryptod/Crypto/Cipher/_mode_cbc.pyi
libcrypto/cryptod/Crypto/Cipher/_mode_ccm.py
libcrypto/cryptod/Crypto/Cipher/_mode_ccm.pyi
libcrypto/cryptod/Crypto/Cipher/_mode_cfb.py
libcrypto-1.4.8.dist-info/licenses/LICENSE
libcrypto-1.4.8.dist-info/METADATA
libcrypto-1.4.8.dist-info/WHEEL
libcrypto-1.4.8.dist-info/entry_points.txt
libcrypto-1.4.8.dist-info/top_level.txt
libcrypto-1.4.8.dist-info/RECORD
