Metadata-Version: 2.4
Name: libcrypto
Version: 1.4.8
Summary: A professional library For Cryptography and Cryptocurrencies in Python.
Home-page: https://github.com/pymmdrza/libcrypto
Author: Mmdrza
Author-email: Mmdrza <pymmdrza@gmail.com>
License: MIT
Project-URL: Homepage, https://libcrypto.readthedocs.io/
Project-URL: Repository, https://github.com/Pymmdrza/libcrypto
Project-URL: Bug Tracker, https://github.com/Pymmdrza/libcrypto/issues
Project-URL: Documentation, https://libcrypto.readthedocs.io
Project-URL: PyPI, https://pypi.org/project/libcrypto/
Keywords: cryptocurrency,bitcoin,ethereum,wallet,bip39,bip32,bip44,mnemonic,private-key,public-key,address,hdwallet,crypto,blockchain,litecoin,dash,dogecoin,bitcoin-cash,secp256k1,cryptography,pure-python
Classifier: Development Status :: 4 - Beta
Classifier: Intended Audience :: Developers
Classifier: License :: OSI Approved :: MIT License
Classifier: Operating System :: OS Independent
Classifier: Programming Language :: Python :: 3
Classifier: Programming Language :: Python :: 3.8
Classifier: Programming Language :: Python :: 3.9
Classifier: Programming Language :: Python :: 3.10
Classifier: Programming Language :: Python :: 3.11
Classifier: Programming Language :: Python :: 3.12
Classifier: Programming Language :: Python :: 3.13
Classifier: Programming Language :: Python :: 3.14
Classifier: Topic :: Security :: Cryptography
Classifier: Topic :: Software Development :: Libraries :: Python Modules
Classifier: Topic :: Office/Business :: Financial
Classifier: Topic :: System :: Systems Administration :: Authentication/Directory
Classifier: Typing :: Typed
Requires-Python: >=3.8
License-File: LICENSE
Requires-Dist: rich
Requires-Dist: typer
Requires-Dist: wheel
Requires-Dist: setuptools
Provides-Extra: dev
Requires-Dist: pytest>=7.0.0; extra == "dev"
Requires-Dist: pytest-cov>=4.0.0; extra == "dev"
Requires-Dist: black>=22.0.0; extra == "dev"
Requires-Dist: flake8>=5.0.0; extra == "dev"
Requires-Dist: isort>=5.10.0; extra == "dev"
Requires-Dist: mypy>=1.0.0; extra == "dev"
Provides-Extra: test
Requires-Dist: pytest>=7.0.0; extra == "test"
Requires-Dist: pytest-cov>=4.0.0; extra == "test"
Dynamic: author
Dynamic: home-page
Dynamic: license-file
Dynamic: requires-python
